[{"time":0.0,"pose":{"rotation":{"radians":0.0},"translation":{"x":1.82,"y":1.07}},"velocity":0,"acceleration":2.0,"curvature":0,"holonomicRotation":180.0,"angularVelocity":0.0,"holonomicAngularVelocity":0.0},{"time":0.10988920674934358,"pose":{"rotation":{"radians":0.0},"translation":{"x":1.83207563776,"y":1.07}},"velocity":0.21977841349868718,"acceleration":2.0000000000000004,"curvature":0,"holonomicRotation":180.0,"angularVelocity":0.0,"holonomicAngularVelocity":0.0},{"time":0.15589016030526115,"pose":{"rotation":{"radians":0.0},"translation":{"x":1.84430174208,"y":1.07}},"velocity":0.3117803206105223,"acceleration":1.9999999999999993,"curvature":0,"holonomicRotation":180.0,"angularVelocity":0.0,"holonomicAngularVelocity":0.0},{"time":0.19151266151354146,"pose":{"rotation":{"radians":0.0},"translation":{"x":1.8566770995200004,"y":1.07}},"velocity":0.383025323027083,"acceleration":2.0000000000000018,"curvature":0,"holonomicRotation":180.0,"angularVelocity":0.0,"holonomicAngularVelocity":0.0},{"time":0.22181184963838188,"pose":{"rotation":{"radians":0.0},"translation":{"x":1.8692004966400002,"y":1.07}},"velocity":0.44362369927676387,"acceleration":2.0000000000000018,"curvature":0,"holonomicRotation":180.0,"angularVelocity":0.0,"holonomicAngularVelocity":0.0},{"time":0.24873825600417873,"pose":{"rotation":{"radians":0.0},"translation":{"x":1.8818707200000004,"y":1.07}},"velocity":0.4974765120083576,"acceleration":2.0,"curvature":0,"holonomicRotation":180.0,"angularVelocity":0.0,"holonomicAngularVelocity":0.0},{"time":0.2732884120485179,"pose":{"rotation":{"radians":0.0},"translation":{"x":1.8946865561600006,"y":1.07}},"velocity":0.5465768240970359,"acceleration":2.0,"curvature":0,"holonomicRotation":180.0,"angularVelocity":0.0,"holonomicAngularVelocity":0.0},{"time":0.2960520084039298,"pose":{"rotation":{"radians":0.0},"translation":{"x":1.9076467916800006,"y":1.07}},"velocity":0.5921040168078597,"acceleration":2.0,"curvature":0,"holonomicRotation":180.0,"angularVelocity":0.0,"holonomicAngularVelocity":1.3306210520908158e-12},{"time":0.3174117406776262,"pose":{"rotation":{"radians":0.0},"translation":{"x":1.9207502131200007,"y":1.07}},"velocity":0.6348234813552525,"acceleration":2.0,"curvature":0,"holonomicRotation":180.00000000000003,"angularVelocity":0.0,"holonomicAngularVelocity":-1.405580918134193e-12},{"time":0.337632354847696,"pose":{"rotation":{"radians":0.0},"translation":{"x":1.9339956070400006,"y":1.07}},"velocity":0.6752647096953921,"acceleration":2.0,"curvature":0,"holonomicRotation":180.0,"angularVelocity":0.0,"holonomicAngularVelocity":0.0},{"time":0.35690581390613496,"pose":{"rotation":{"radians":0.0},"translation":{"x":1.9473817600000007,"y":1.07}},"velocity":0.71381162781227,"acceleration":2.0,"curvature":0,"holonomicRotation":180.0,"angularVelocity":0.0,"holonomicAngularVelocity":0.0},{"time":0.3753764224881482,"pose":{"rotation":{"radians":0.0},"translation":{"x":1.9609074585600008,"y":1.07}},"velocity":0.7507528449762965,"acceleration":2.0,"curvature":0,"holonomicRotation":180.0,"angularVelocity":0.0,"holonomicAngularVelocity":0.0},{"time":0.3931558078930041,"pose":{"rotation":{"radians":0.0},"translation":{"x":1.9745714892800008,"y":1.07}},"velocity":0.7863116157860082,"acceleration":1.9999999999999938,"curvature":0,"holonomicRotation":180.0,"angularVelocity":0.0,"holonomicAngularVelocity":0.0},{"time":0.41033235153957925,"pose":{"rotation":{"radians":0.0},"translation":{"x":1.988372638720001,"y":1.07}},"velocity":0.8206647030791585,"acceleration":2.0,"curvature":0,"holonomicRotation":180.0,"angularVelocity":0.0,"holonomicAngularVelocity":1.7075181749363585e-12},{"time":0.42697739218839303,"pose":{"rotation":{"radians":0.0},"translation":{"x":2.002309693440001,"y":1.07}},"velocity":0.8539547843767861,"acceleration":2.0,"curvature":0,"holonomicRotation":180.00000000000003,"angularVelocity":0.0,"holonomicAngularVelocity":-1.7574572090275637e-12},{"time":0.4431494556016071,"pose":{"rotation":{"radians":0.0},"translation":{"x":2.016381440000001,"y":1.07}},"velocity":0.8862989112032144,"acceleration":2.0000000000000067,"curvature":0,"holonomicRotation":180.0,"angularVelocity":0.0,"holonomicAngularVelocity":0.0},{"time":0.45889722701276014,"pose":{"rotation":{"radians":0.0},"translation":{"x":2.030586664960001,"y":1.07}},"velocity":0.9177944540255205,"acceleration":2.000000000000007,"curvature":0,"holonomicRotation":180.0,"angularVelocity":0.0,"holonomicAngularVelocity":0.0},{"time":0.4742616945105319,"pose":{"rotation":{"radians":0.0},"translation":{"x":2.0449241548800012,"y":1.07}},"velocity":0.948523389021064,"acceleration":2.0,"curvature":0,"holonomicRotation":180.0,"angularVelocity":0.0,"holonomicAngularVelocity":0.0},{"time":0.4892777292295256,"pose":{"rotation":{"radians":0.0},"translation":{"x":2.059392696320001,"y":1.07}},"velocity":0.9785554584590515,"acceleration":2.0,"curvature":0,"holonomicRotation":180.0,"angularVelocity":0.0,"holonomicAngularVelocity":-1.933772730242083e-12},{"time":0.5039752730442251,"pose":{"rotation":{"radians":0.0},"translation":{"x":2.0739910758400013,"y":1.07}},"velocity":1.0079505460884504,"acceleration":2.0,"curvature":0,"holonomicRotation":179.99999999999997,"angularVelocity":0.0,"holonomicAngularVelocity":1.973048367232474e-12},{"time":0.5183802465372318,"pose":{"rotation":{"radians":0.0},"translation":{"x":2.0887180800000014,"y":1.07}},"velocity":1.0367604930744638,"acceleration":2.0,"curvature":0,"holonomicRotation":180.0,"angularVelocity":0.0,"holonomicAngularVelocity":0.0},{"time":0.5325152536406831,"pose":{"rotation":{"radians":0.0},"translation":{"x":2.1035724953600012,"y":1.07}},"velocity":1.0650305072813666,"acceleration":2.0000000000000155,"curvature":0,"holonomicRotation":180.0,"angularVelocity":0.0,"holonomicAngularVelocity":0.0},{"time":0.5464001358711412,"pose":{"rotation":{"radians":0.0},"translation":{"x":2.118553108480002,"y":1.07}},"velocity":1.092800271742283,"acceleration":2.0,"curvature":0,"holonomicRotation":180.0,"angularVelocity":0.0,"holonomicAngularVelocity":0.0},{"time":0.5600524135471621,"pose":{"rotation":{"radians":0.0},"translation":{"x":2.1336587059200016,"y":1.07}},"velocity":1.1201048270943246,"acceleration":2.0,"curvature":0,"holonomicRotation":180.0,"angularVelocity":0.0,"holonomicAngularVelocity":2.1154617432353854e-12},{"time":0.5734876408781635,"pose":{"rotation":{"radians":0.0},"translation":{"x":2.1488880742400016,"y":1.07}},"velocity":1.1469752817563275,"acceleration":2.0,"curvature":0,"holonomicRotation":180.00000000000003,"angularVelocity":0.0,"holonomicAngularVelocity":-2.1479439311215688e-12},{"time":0.5867196945731421,"pose":{"rotation":{"radians":0.0},"translation":{"x":2.1642400000000013,"y":1.07}},"velocity":1.1734393891462847,"acceleration":2.0,"curvature":0,"holonomicRotation":180.0,"angularVelocity":0.0,"holonomicAngularVelocity":-2.1793590086941912e-12},{"time":0.5997610105366985,"pose":{"rotation":{"radians":0.0},"translation":{"x":2.179713269760002,"y":1.07}},"velocity":1.1995220210733974,"acceleration":2.0,"curvature":0,"holonomicRotation":179.99999999999997,"angularVelocity":0.0,"holonomicAngularVelocity":0.0},{"time":0.612622779596059,"pose":{"rotation":{"radians":0.0},"translation":{"x":2.1953066700800017,"y":1.07}},"velocity":1.2252455591921185,"acceleration":2.0,"curvature":0,"holonomicRotation":179.99999999999997,"angularVelocity":0.0,"holonomicAngularVelocity":4.478564176396672e-12},{"time":0.6253151105802591,"pose":{"rotation":{"radians":0.0},"translation":{"x":2.211018987520002,"y":1.07}},"velocity":1.2506302211605187,"acceleration":2.0,"curvature":0,"holonomicRotation":180.00000000000003,"angularVelocity":0.0,"holonomicAngularVelocity":-2.267920614187335e-12},{"time":0.6378471671489977,"pose":{"rotation":{"radians":0.0},"translation":{"x":2.2268490086400017,"y":1.07}},"velocity":1.2756943342979958,"acceleration":2.0,"curvature":0,"holonomicRotation":180.0,"angularVelocity":0.0,"holonomicAngularVelocity":0.0},{"time":0.6502272833402191,"pose":{"rotation":{"radians":0.0},"translation":{"x":2.242795520000002,"y":1.07}},"velocity":1.3004545666804386,"acceleration":2.0,"curvature":0,"holonomicRotation":180.0,"angularVelocity":0.0,"holonomicAngularVelocity":0.0},{"time":0.6624630617325029,"pose":{"rotation":{"radians":0.0},"translation":{"x":2.2588573081600023,"y":1.07}},"velocity":1.3249261234650063,"acceleration":2.0,"curvature":0,"holonomicRotation":180.0,"angularVelocity":0.0,"holonomicAngularVelocity":0.0},{"time":0.6745614573039297,"pose":{"rotation":{"radians":0.0},"translation":{"x":2.2750331596800017,"y":1.07}},"velocity":1.3491229146078598,"acceleration":2.0,"curvature":0,"holonomicRotation":180.0,"angularVelocity":0.0,"holonomicAngularVelocity":0.0},{"time":0.6865288494448005,"pose":{"rotation":{"radians":0.0},"translation":{"x":2.291321861120002,"y":1.07}},"velocity":1.3730576988896013,"acceleration":1.9999999999999813,"curvature":0,"holonomicRotation":180.0,"angularVelocity":0.0,"holonomicAngularVelocity":0.0},{"time":0.6983711040986748,"pose":{"rotation":{"radians":0.0},"translation":{"x":2.3077221990400023,"y":1.07}},"velocity":1.3967422081973497,"acceleration":2.0,"curvature":0,"holonomicRotation":180.0,"angularVelocity":0.0,"holonomicAngularVelocity":0.0},{"time":0.710093627629485,"pose":{"rotation":{"radians":0.0},"translation":{"x":2.324232960000002,"y":1.07}},"velocity":1.4201872552589703,"acceleration":2.0,"curvature":0,"holonomicRotation":180.0,"angularVelocity":0.0,"holonomicAngularVelocity":0.0},{"time":0.7217014137162276,"pose":{"rotation":{"radians":0.0},"translation":{"x":2.340852930560002,"y":1.07}},"velocity":1.4434028274324555,"acceleration":2.0,"curvature":0,"holonomicRotation":180.0,"angularVelocity":0.0,"holonomicAngularVelocity":0.0},{"time":0.7331990843420374,"pose":{"rotation":{"radians":0.0},"translation":{"x":2.3575808972800023,"y":1.07}},"velocity":1.4663981686840748,"acceleration":1.9999999999999807,"curvature":0,"holonomicRotation":180.0,"angularVelocity":0.0,"holonomicAngularVelocity":0.0},{"time":0.7445909257572255,"pose":{"rotation":{"radians":0.0},"translation":{"x":2.3744156467200024,"y":1.07}},"velocity":1.489181851514451,"acceleration":2.0,"curvature":0,"holonomicRotation":180.0,"angularVelocity":0.0,"holonomicAngularVelocity":0.0},{"time":0.7558809201454963,"pose":{"rotation":{"radians":0.0},"translation":{"x":2.3913559654400025,"y":1.07}},"velocity":1.5117618402909927,"acceleration":2.0,"curvature":0,"holonomicRotation":180.0,"angularVelocity":0.0,"holonomicAngularVelocity":0.0},{"time":0.7670727736010465,"pose":{"rotation":{"radians":0.0},"translation":{"x":2.4084006400000026,"y":1.07}},"velocity":1.534145547202093,"acceleration":2.0,"curvature":0,"holonomicRotation":180.0,"angularVelocity":0.0,"holonomicAngularVelocity":0.0},{"time":0.7781699409255038,"pose":{"rotation":{"radians":0.0},"translation":{"x":2.4255484569600023,"y":1.07}},"velocity":1.5563398818510075,"acceleration":1.99999999999998,"curvature":0,"holonomicRotation":180.0,"angularVelocity":0.0,"holonomicAngularVelocity":0.0},{"time":0.7891756476729389,"pose":{"rotation":{"radians":0.0},"translation":{"x":2.442798202880003,"y":1.07}},"velocity":1.5783512953458776,"acceleration":2.0,"curvature":0,"holonomicRotation":180.0,"angularVelocity":0.0,"holonomicAngularVelocity":0.0},{"time":0.8000929098048567,"pose":{"rotation":{"radians":0.0},"translation":{"x":2.460148664320003,"y":1.07}},"velocity":1.6001858196097132,"acceleration":2.0,"curvature":0,"holonomicRotation":180.0,"angularVelocity":0.0,"holonomicAngularVelocity":0.0},{"time":0.8109245512623245,"pose":{"rotation":{"radians":0.0},"translation":{"x":2.4775986278400026,"y":1.07}},"velocity":1.6218491025246489,"acceleration":2.0,"curvature":0,"holonomicRotation":180.0,"angularVelocity":0.0,"holonomicAngularVelocity":0.0},{"time":0.8216732197169399,"pose":{"rotation":{"radians":0.0},"translation":{"x":2.4951468800000027,"y":1.07}},"velocity":1.6433464394338795,"acceleration":2.0,"curvature":0,"holonomicRotation":180.0,"angularVelocity":0.0,"holonomicAngularVelocity":0.0},{"time":0.8323414007244881,"pose":{"rotation":{"radians":0.0},"translation":{"x":2.512792207360003,"y":1.07}},"velocity":1.664682801448976,"acceleration":2.0,"curvature":0,"holonomicRotation":180.0,"angularVelocity":0.0,"holonomicAngularVelocity":0.0},{"time":0.8429314304734417,"pose":{"rotation":{"radians":0.0},"translation":{"x":2.5305333964800028,"y":1.07}},"velocity":1.685862860946883,"acceleration":2.0,"curvature":0,"holonomicRotation":180.0,"angularVelocity":0.0,"holonomicAngularVelocity":2.70320541840843e-12},{"time":0.8534455072938181,"pose":{"rotation":{"radians":0.0},"translation":{"x":2.5483692339200026,"y":1.07}},"velocity":1.706891014587636,"acceleration":2.0,"curvature":0,"holonomicRotation":180.00000000000003,"angularVelocity":0.0,"holonomicAngularVelocity":-5.444670342124163e-12},{"time":0.8638857020694363,"pose":{"rotation":{"radians":0.0},"translation":{"x":2.566298506240003,"y":1.07}},"velocity":1.7277714041388725,"acceleration":2.0000000000000213,"curvature":0,"holonomicRotation":179.99999999999997,"angularVelocity":0.0,"holonomicAngularVelocity":2.7412211940310007e-12},{"time":0.8742539676775865,"pose":{"rotation":{"radians":0.0},"translation":{"x":2.5843200000000026,"y":1.07}},"velocity":1.748507935355173,"acceleration":2.0,"curvature":0,"holonomicRotation":180.0,"angularVelocity":0.0,"holonomicAngularVelocity":0.0},{"time":0.884552147563954,"pose":{"rotation":{"radians":0.0},"translation":{"x":2.602432501760003,"y":1.07}},"velocity":1.769104295127908,"acceleration":2.0,"curvature":0,"holonomicRotation":180.0,"angularVelocity":0.0,"holonomicAngularVelocity":2.7783152611610813e-12},{"time":0.8947819835468317,"pose":{"rotation":{"radians":0.0},"translation":{"x":2.620634798080003,"y":1.07}},"velocity":1.7895639670936636,"acceleration":2.0000000000000218,"curvature":0,"holonomicRotation":180.00000000000003,"angularVelocity":0.0,"holonomicAngularVelocity":-2.796548226960723e-12},{"time":0.9049451229328785,"pose":{"rotation":{"radians":0.0},"translation":{"x":2.638925675520003,"y":1.07}},"velocity":1.8098902458657573,"acceleration":2.0,"curvature":0,"holonomicRotation":180.0,"angularVelocity":0.0,"holonomicAngularVelocity":0.0},{"time":0.9150431250165222,"pose":{"rotation":{"radians":0.0},"translation":{"x":2.657303920640003,"y":1.07}},"velocity":1.8300862500330446,"acceleration":2.0,"curvature":0,"holonomicRotation":180.0,"angularVelocity":0.0,"holonomicAngularVelocity":2.8324437618721062e-12},{"time":0.9250774670264121,"pose":{"rotation":{"radians":0.0},"translation":{"x":2.675768320000003,"y":1.07}},"velocity":1.8501549340528245,"acceleration":2.0,"curvature":0,"holonomicRotation":180.00000000000003,"angularVelocity":0.0,"holonomicAngularVelocity":-2.850127773465967e-12},{"time":0.9350495495747819,"pose":{"rotation":{"radians":0.0},"translation":{"x":2.694317660160003,"y":1.07}},"velocity":1.870099099149564,"acceleration":2.0,"curvature":0,"holonomicRotation":180.0,"angularVelocity":0.0,"holonomicAngularVelocity":0.0},{"time":0.9449607016590704,"pose":{"rotation":{"radians":0.0},"translation":{"x":2.712950727680003,"y":1.07}},"velocity":1.889921403318141,"acceleration":2.0,"curvature":0,"holonomicRotation":180.0,"angularVelocity":0.0,"holonomicAngularVelocity":0.0},{"time":0.95481218525949,"pose":{"rotation":{"radians":0.0},"translation":{"x":2.731666309120003,"y":1.07}},"velocity":1.9096243705189804,"acceleration":2.0000000000000226,"curvature":0,"holonomicRotation":180.0,"angularVelocity":0.0,"holonomicAngularVelocity":0.0},{"time":0.9646051995713079,"pose":{"rotation":{"radians":0.0},"translation":{"x":2.7504631910400033,"y":1.07}},"velocity":1.9292103991426162,"acceleration":2.0,"curvature":0,"holonomicRotation":180.0,"angularVelocity":0.0,"holonomicAngularVelocity":0.0},{"time":0.9743408849063055,"pose":{"rotation":{"radians":0.0},"translation":{"x":2.769340160000003,"y":1.07}},"velocity":1.9486817698126115,"acceleration":2.0,"curvature":0,"holonomicRotation":180.0,"angularVelocity":0.0,"holonomicAngularVelocity":0.0},{"time":0.9840203262941285,"pose":{"rotation":{"radians":0.0},"translation":{"x":2.7882960025600037,"y":1.07}},"velocity":1.9680406525882574,"acceleration":2.0,"curvature":0,"holonomicRotation":180.0,"angularVelocity":0.0,"holonomicAngularVelocity":0.0},{"time":0.9936445568109367,"pose":{"rotation":{"radians":0.0},"translation":{"x":2.8073295052800034,"y":1.07}},"velocity":1.987289113621874,"acceleration":2.000000000000023,"curvature":0,"holonomicRotation":180.0,"angularVelocity":0.0,"holonomicAngularVelocity":0.0},{"time":1.0032145606598832,"pose":{"rotation":{"radians":0.0},"translation":{"x":2.826439454720003,"y":1.07}},"velocity":2.0064291213197674,"acceleration":2.000000000000023,"curvature":0,"holonomicRotation":180.0,"angularVelocity":0.0,"holonomicAngularVelocity":0.0},{"time":1.012731276025384,"pose":{"rotation":{"radians":0.0},"translation":{"x":2.845624637440003,"y":1.07}},"velocity":2.0254625520507687,"acceleration":2.0,"curvature":0,"holonomicRotation":180.0,"angularVelocity":0.0,"holonomicAngularVelocity":0.0},{"time":1.0221955977209074,"pose":{"rotation":{"radians":0.0},"translation":{"x":2.8648838400000036,"y":1.07}},"velocity":2.0443911954418157,"acceleration":2.0,"curvature":0,"holonomicRotation":180.0,"angularVelocity":0.0,"holonomicAngularVelocity":0.0},{"time":1.0316083796480149,"pose":{"rotation":{"radians":0.0},"translation":{"x":2.8842158489600034,"y":1.07}},"velocity":2.0632167592960307,"acceleration":2.0,"curvature":0,"holonomicRotation":180.0,"angularVelocity":0.0,"holonomicAngularVelocity":0.0},{"time":1.0409704370826305,"pose":{"rotation":{"radians":0.0},"translation":{"x":2.9036194508800035,"y":1.07}},"velocity":2.081940874165262,"acceleration":2.0,"curvature":0,"holonomicRotation":180.0,"angularVelocity":0.0,"holonomicAngularVelocity":0.0},{"time":1.0502825488029413,"pose":{"rotation":{"radians":0.0},"translation":{"x":2.9230934323200035,"y":1.07}},"velocity":2.1005650976058834,"acceleration":2.0,"curvature":0,"holonomicRotation":180.0,"angularVelocity":0.0,"holonomicAngularVelocity":3.0683347463136462e-12},{"time":1.0595454590719562,"pose":{"rotation":{"radians":0.0},"translation":{"x":2.9426365798400034,"y":1.07}},"velocity":2.1190909181439133,"acceleration":2.0,"curvature":0,"holonomicRotation":180.00000000000003,"angularVelocity":0.0,"holonomicAngularVelocity":-3.0844815139471443e-12},{"time":1.068759879486502,"pose":{"rotation":{"radians":0.0},"translation":{"x":2.9622476800000035,"y":1.07}},"velocity":2.137519758973005,"acceleration":2.0,"curvature":0,"holonomicRotation":180.0,"angularVelocity":0.0,"holonomicAngularVelocity":0.0},{"time":1.0779264907033328,"pose":{"rotation":{"radians":0.0},"translation":{"x":2.9819255193600034,"y":1.07}},"velocity":2.1558529814066665,"acceleration":2.0,"curvature":0,"holonomicRotation":180.0,"angularVelocity":0.0,"holonomicAngularVelocity":0.0},{"time":1.0870459440520452,"pose":{"rotation":{"radians":0.0},"translation":{"x":3.0016688844800035,"y":1.07}},"velocity":2.1740918881040914,"acceleration":2.0,"curvature":0,"holonomicRotation":180.0,"angularVelocity":0.0,"holonomicAngularVelocity":0.0},{"time":1.0961188630436036,"pose":{"rotation":{"radians":0.0},"translation":{"x":3.0214765619200037,"y":1.07}},"velocity":2.192237726087208,"acceleration":2.0,"curvature":0,"holonomicRotation":180.0,"angularVelocity":0.0,"holonomicAngularVelocity":-3.14852851734165e-12},{"time":1.1051458447824893,"pose":{"rotation":{"radians":0.0},"translation":{"x":3.0413473382400036,"y":1.07}},"velocity":2.2102916895649796,"acceleration":2.0,"curvature":0,"holonomicRotation":179.99999999999997,"angularVelocity":0.0,"holonomicAngularVelocity":3.1644314146952385e-12},{"time":1.1141274612897762,"pose":{"rotation":{"radians":0.0},"translation":{"x":3.0612800000000036,"y":1.07}},"velocity":2.2282549225795534,"acceleration":2.0,"curvature":0,"holonomicRotation":180.0,"angularVelocity":0.0,"holonomicAngularVelocity":0.0},{"time":1.1230642607437928,"pose":{"rotation":{"radians":0.0},"translation":{"x":3.0812733337600036,"y":1.07}},"velocity":2.2461285214875866,"acceleration":2.0,"curvature":0,"holonomicRotation":180.0,"angularVelocity":0.0,"holonomicAngularVelocity":0.0},{"time":1.1319567686444576,"pose":{"rotation":{"radians":0.0},"translation":{"x":3.1013261260800036,"y":1.07}},"velocity":2.2639135372889156,"acceleration":1.99999999999995,"curvature":0,"holonomicRotation":180.0,"angularVelocity":0.0,"holonomicAngularVelocity":-3.2119570500144517e-12},{"time":1.1408054889068522,"pose":{"rotation":{"radians":0.0},"translation":{"x":3.1214371635200036,"y":1.07}},"velocity":2.281610977813705,"acceleration":2.0,"curvature":0,"holonomicRotation":179.99999999999997,"angularVelocity":0.0,"holonomicAngularVelocity":3.2277531791354467e-12},{"time":1.149610904889129,"pose":{"rotation":{"radians":0.0},"translation":{"x":3.1416052326400035,"y":1.07}},"velocity":2.2992218097782584,"acceleration":2.0,"curvature":0,"holonomicRotation":180.0,"angularVelocity":0.0,"holonomicAngularVelocity":3.2435337677555047e-12},{"time":1.1583734803594228,"pose":{"rotation":{"radians":0.0},"translation":{"x":3.1618291200000037,"y":1.07}},"velocity":2.316746960718846,"acceleration":2.0,"curvature":0,"holonomicRotation":180.00000000000003,"angularVelocity":0.0,"holonomicAngularVelocity":-3.25930305090239e-12},{"time":1.1670936604060542,"pose":{"rotation":{"radians":0.0},"translation":{"x":3.182107612160004,"y":1.07}},"velocity":2.334187320812109,"acceleration":2.0,"curvature":0,"holonomicRotation":180.0,"angularVelocity":0.0,"holonomicAngularVelocity":0.0},{"time":1.1757718722949628,"pose":{"rotation":{"radians":0.0},"translation":{"x":3.2024394956800037,"y":1.07}},"velocity":2.3515437445899257,"acceleration":1.999999999999949,"curvature":0,"holonomicRotation":180.0,"angularVelocity":0.0,"holonomicAngularVelocity":0.0},{"time":1.184408526277991,"pose":{"rotation":{"radians":0.0},"translation":{"x":3.222823557120004,"y":1.07}},"velocity":2.368817052555982,"acceleration":2.0,"curvature":0,"holonomicRotation":180.0,"angularVelocity":0.0,"holonomicAngularVelocity":0.0},{"time":1.1930040163553526,"pose":{"rotation":{"radians":0.0},"translation":{"x":3.243258583040004,"y":1.07}},"velocity":2.3860080327107056,"acceleration":2.0000000000000515,"curvature":0,"holonomicRotation":180.0,"angularVelocity":0.0,"holonomicAngularVelocity":0.0},{"time":1.2015587209953589,"pose":{"rotation":{"radians":0.0},"translation":{"x":3.263743360000004,"y":1.07}},"velocity":2.4031174419907178,"acceleration":1.999999999999948,"curvature":0,"holonomicRotation":180.0,"angularVelocity":0.0,"holonomicAngularVelocity":0.0},{"time":1.2100730038142338,"pose":{"rotation":{"radians":0.0},"translation":{"x":3.284276674560004,"y":1.07}},"velocity":2.4201460076284675,"acceleration":2.0,"curvature":0,"holonomicRotation":180.0,"angularVelocity":0.0,"holonomicAngularVelocity":0.0},{"time":1.2185472142186378,"pose":{"rotation":{"radians":0.0},"translation":{"x":3.304857313280004,"y":1.07}},"velocity":2.4370944284372755,"acceleration":2.0,"curvature":0,"holonomicRotation":180.0,"angularVelocity":0.0,"holonomicAngularVelocity":0.0},{"time":1.2269816880133146,"pose":{"rotation":{"radians":0.0},"translation":{"x":3.325484062720004,"y":1.07}},"velocity":2.4539633760266293,"acceleration":2.0,"curvature":0,"holonomicRotation":180.0,"angularVelocity":0.0,"holonomicAngularVelocity":0.0},{"time":1.2353767479760993,"pose":{"rotation":{"radians":0.0},"translation":{"x":3.346155709440004,"y":1.07}},"velocity":2.4707534959521986,"acceleration":2.0,"curvature":0,"holonomicRotation":180.0,"angularVelocity":0.0,"holonomicAngularVelocity":0.0},{"time":1.2437327044023578,"pose":{"rotation":{"radians":0.0},"translation":{"x":3.3668710400000044,"y":1.07}},"velocity":2.487465408804716,"acceleration":2.0000000000000533,"curvature":0,"holonomicRotation":180.0,"angularVelocity":0.0,"holonomicAngularVelocity":0.0},{"time":1.2520498556207744,"pose":{"rotation":{"radians":0.0},"translation":{"x":3.3876288409600037,"y":1.07}},"velocity":2.5040997112415493,"acceleration":2.0,"curvature":0,"holonomicRotation":180.0,"angularVelocity":0.0,"holonomicAngularVelocity":0.0},{"time":1.2603284884822696,"pose":{"rotation":{"radians":0.0},"translation":{"x":3.408427898880004,"y":1.07}},"velocity":2.5206569769645393,"acceleration":1.9999999999999463,"curvature":0,"holonomicRotation":180.0,"angularVelocity":0.0,"holonomicAngularVelocity":0.0},{"time":1.2685688788236933,"pose":{"rotation":{"radians":0.0},"translation":{"x":3.429267000320004,"y":1.07}},"velocity":2.5371377576473866,"acceleration":2.0,"curvature":0,"holonomicRotation":180.0,"angularVelocity":0.0,"holonomicAngularVelocity":0.0},{"time":1.2767712919078351,"pose":{"rotation":{"radians":0.0},"translation":{"x":3.450144931840004,"y":1.07}},"velocity":2.5535425838156702,"acceleration":2.0,"curvature":0,"holonomicRotation":180.0,"angularVelocity":0.0,"holonomicAngularVelocity":0.0},{"time":1.2849359828411693,"pose":{"rotation":{"radians":0.0},"translation":{"x":3.471060480000004,"y":1.07}},"velocity":2.5698719656823386,"acceleration":2.0,"curvature":0,"holonomicRotation":180.0,"angularVelocity":0.0,"holonomicAngularVelocity":0.0},{"time":1.2930631969706672,"pose":{"rotation":{"radians":0.0},"translation":{"x":3.4920124313600045,"y":1.07}},"velocity":2.5861263939413344,"acceleration":2.0,"curvature":0,"holonomicRotation":180.0,"angularVelocity":0.0,"holonomicAngularVelocity":0.0},{"time":1.3011531702609043,"pose":{"rotation":{"radians":0.0},"translation":{"x":3.512999572480004,"y":1.07}},"velocity":2.6023063405218085,"acceleration":2.0,"curvature":0,"holonomicRotation":180.0,"angularVelocity":0.0,"holonomicAngularVelocity":0.0},{"time":1.3092061296526236,"pose":{"rotation":{"radians":0.0},"translation":{"x":3.5340206899200046,"y":1.07}},"velocity":2.6184122593052472,"acceleration":2.0,"curvature":0,"holonomicRotation":180.0,"angularVelocity":0.0,"holonomicAngularVelocity":0.0},{"time":1.3172222934038134,"pose":{"rotation":{"radians":0.0},"translation":{"x":3.555074570240004,"y":1.07}},"velocity":2.6344445868076267,"acceleration":2.0,"curvature":0,"holonomicRotation":180.0,"angularVelocity":0.0,"holonomicAngularVelocity":0.0},{"time":1.3252018714143148,"pose":{"rotation":{"radians":0.0},"translation":{"x":3.5761600000000042,"y":1.07}},"velocity":2.6504037428286296,"acceleration":2.0,"curvature":0,"holonomicRotation":180.0,"angularVelocity":0.0,"holonomicAngularVelocity":0.0},{"time":1.3331450655348807,"pose":{"rotation":{"radians":0.0},"translation":{"x":3.5972757657600036,"y":1.07}},"velocity":2.6662901310697618,"acceleration":2.000000000000056,"curvature":0,"holonomicRotation":180.0,"angularVelocity":0.0,"holonomicAngularVelocity":0.0},{"time":1.3410520698615702,"pose":{"rotation":{"radians":0.0},"translation":{"x":3.618420654080004,"y":1.07}},"velocity":2.6821041397231404,"acceleration":1.9999999999999438,"curvature":0,"holonomicRotation":180.0,"angularVelocity":0.0,"holonomicAngularVelocity":0.0},{"time":1.3489230710162838,"pose":{"rotation":{"radians":0.0},"translation":{"x":3.639593451520004,"y":1.07}},"velocity":2.6978461420325677,"acceleration":2.0,"curvature":0,"holonomicRotation":180.0,"angularVelocity":0.0,"holonomicAngularVelocity":0.0},{"time":1.3567582484142127,"pose":{"rotation":{"radians":0.0},"translation":{"x":3.6607929446400043,"y":1.07}},"velocity":2.7135164968284253,"acceleration":2.0,"curvature":0,"holonomicRotation":180.0,"angularVelocity":0.0,"holonomicAngularVelocity":0.0},{"time":1.3645577745189108,"pose":{"rotation":{"radians":0.0},"translation":{"x":3.6820179200000043,"y":1.07}},"velocity":2.7291155490378216,"acceleration":2.0,"curvature":0,"holonomicRotation":180.0,"angularVelocity":0.0,"holonomicAngularVelocity":0.0},{"time":1.3723218150856609,"pose":{"rotation":{"radians":0.0},"translation":{"x":3.7032671641600046,"y":1.07}},"velocity":2.7446436301713217,"acceleration":2.0,"curvature":0,"holonomicRotation":180.0,"angularVelocity":0.0,"holonomicAngularVelocity":0.0},{"time":1.380050529393762,"pose":{"rotation":{"radians":0.0},"translation":{"x":3.724539463680004,"y":1.07}},"velocity":2.760101058787524,"acceleration":2.0,"curvature":0,"holonomicRotation":180.0,"angularVelocity":0.0,"holonomicAngularVelocity":0.0},{"time":1.3877440704683277,"pose":{"rotation":{"radians":0.0},"translation":{"x":3.7458336051200045,"y":1.07}},"velocity":2.7754881409366554,"acceleration":2.0,"curvature":0,"holonomicRotation":180.0,"angularVelocity":0.0,"holonomicAngularVelocity":0.0},{"time":1.3954025852921452,"pose":{"rotation":{"radians":0.0},"translation":{"x":3.767148375040004,"y":1.07}},"velocity":2.7908051705842905,"acceleration":2.0,"curvature":0,"holonomicRotation":180.0,"angularVelocity":0.0,"holonomicAngularVelocity":0.0},{"time":1.403026215008117,"pose":{"rotation":{"radians":0.0},"translation":{"x":3.7884825600000043,"y":1.07}},"velocity":2.806052430016234,"acceleration":2.0,"curvature":0,"holonomicRotation":180.0,"angularVelocity":0.0,"holonomicAngularVelocity":0.0},{"time":1.4106150951127676,"pose":{"rotation":{"radians":0.0},"translation":{"x":3.809834946560004,"y":1.07}},"velocity":2.8212301902255352,"acceleration":2.0,"curvature":0,"holonomicRotation":180.0,"angularVelocity":0.0,"holonomicAngularVelocity":0.0},{"time":1.4181693556412798,"pose":{"rotation":{"radians":0.0},"translation":{"x":3.8312043212800044,"y":1.07}},"velocity":2.8363387112825595,"acceleration":2.0,"curvature":0,"holonomicRotation":180.0,"angularVelocity":0.0,"holonomicAngularVelocity":0.0},{"time":1.4256891213444824,"pose":{"rotation":{"radians":0.0},"translation":{"x":3.8525894707200043,"y":1.07}},"velocity":2.8513782426889653,"acceleration":2.000000000000059,"curvature":0,"holonomicRotation":180.0,"angularVelocity":0.0,"holonomicAngularVelocity":0.0},{"time":1.4331745118582044,"pose":{"rotation":{"radians":0.0},"translation":{"x":3.8739891814400043,"y":1.07}},"velocity":2.8663490237164093,"acceleration":2.0,"curvature":0,"holonomicRotation":180.0,"angularVelocity":0.0,"holonomicAngularVelocity":0.0},{"time":1.4406256418653676,"pose":{"rotation":{"radians":0.0},"translation":{"x":3.8954022400000037,"y":1.07}},"velocity":2.881251283730735,"acceleration":1.9999999999999405,"curvature":0,"holonomicRotation":180.0,"angularVelocity":0.0,"holonomicAngularVelocity":0.0},{"time":1.448042621251185,"pose":{"rotation":{"radians":0.0},"translation":{"x":3.9168274329600044,"y":1.07}},"velocity":2.8960852425023704,"acceleration":2.00000000000006,"curvature":0,"holonomicRotation":180.0,"angularVelocity":0.0,"holonomicAngularVelocity":0.0},{"time":1.4554255552517974,"pose":{"rotation":{"radians":0.0},"translation":{"x":3.938263546880004,"y":1.07}},"velocity":2.9108511105035952,"acceleration":2.0,"curvature":0,"holonomicRotation":180.0,"angularVelocity":0.0,"holonomicAngularVelocity":0.0},{"time":1.4627745445966724,"pose":{"rotation":{"radians":0.0},"translation":{"x":3.959709368320004,"y":1.07}},"velocity":2.9255490891933453,"acceleration":2.0,"curvature":0,"holonomicRotation":180.0,"angularVelocity":0.0,"holonomicAngularVelocity":0.0},{"time":1.4700896856450638,"pose":{"rotation":{"radians":0.0},"translation":{"x":3.981163683840004,"y":1.07}},"velocity":2.940179371290128,"acceleration":2.0,"curvature":0,"holonomicRotation":180.0,"angularVelocity":0.0,"holonomicAngularVelocity":0.0},{"time":1.477371070516816,"pose":{"rotation":{"radians":0.0},"translation":{"x":4.002625280000005,"y":1.07}},"velocity":2.9547421410336323,"acceleration":2.0,"curvature":0,"holonomicRotation":180.0,"angularVelocity":0.0,"holonomicAngularVelocity":0.0},{"time":1.4846187872177834,"pose":{"rotation":{"radians":0.0},"translation":{"x":4.024092943360004,"y":1.07}},"velocity":2.9692375744355672,"acceleration":2.0,"curvature":0,"holonomicRotation":180.0,"angularVelocity":0.0,"holonomicAngularVelocity":0.0},{"time":1.4918329197601192,"pose":{"rotation":{"radians":0.0},"translation":{"x":4.045565460480004,"y":1.07}},"velocity":2.983665839520239,"acceleration":2.0,"curvature":0,"holonomicRotation":180.0,"angularVelocity":0.0,"holonomicAngularVelocity":0.0},{"time":1.4990135482776674,"pose":{"rotation":{"radians":0.0},"translation":{"x":4.067041617920005,"y":1.07}},"velocity":2.9980270965553353,"acceleration":2.0,"curvature":0,"holonomicRotation":180.0,"angularVelocity":0.0,"holonomicAngularVelocity":0.0},{"time":1.5061754313349596,"pose":{"rotation":{"radians":0.0},"translation":{"x":4.088520202240004,"y":1.07}},"velocity":3.0,"acceleration":0.2754727253827373,"curvature":0,"holonomicRotation":180.0,"angularVelocity":0.0,"holonomicAngularVelocity":0.0},{"time":1.513335363921626,"pose":{"rotation":{"radians":0.0},"translation":{"x":4.110000000000004,"y":1.07}},"velocity":3.0,"acceleration":0.0,"curvature":0,"holonomicRotation":180.0,"angularVelocity":0.0,"holonomicAngularVelocity":0.0},{"time":1.520495296508293,"pose":{"rotation":{"radians":0.0},"translation":{"x":4.131479797760004,"y":1.07}},"velocity":3.0,"acceleration":0.0,"curvature":0,"holonomicRotation":180.0,"angularVelocity":0.0,"holonomicAngularVelocity":0.0},{"time":1.5276668243481173,"pose":{"rotation":{"radians":0.0},"translation":{"x":4.152958382080004,"y":1.07}},"velocity":2.9899605215855267,"acceleration":-1.399907891136235,"curvature":0,"holonomicRotation":180.0,"angularVelocity":0.0,"holonomicAngularVelocity":0.0},{"time":1.534866919014178,"pose":{"rotation":{"radians":0.0},"translation":{"x":4.1744345395200035,"y":1.07}},"velocity":2.9755603322534054,"acceleration":-2.0,"curvature":0,"holonomicRotation":180.0,"angularVelocity":0.0,"holonomicAngularVelocity":0.0},{"time":1.5421007989343336,"pose":{"rotation":{"radians":0.0},"translation":{"x":4.195907056640004,"y":1.07}},"velocity":2.961092572413094,"acceleration":-2.0,"curvature":0,"holonomicRotation":180.0,"angularVelocity":0.0,"holonomicAngularVelocity":0.0},{"time":1.5493685499548153,"pose":{"rotation":{"radians":0.0},"translation":{"x":4.217374720000004,"y":1.07}},"velocity":2.946557070372131,"acceleration":-1.999999999999939,"curvature":0,"holonomicRotation":180.0,"angularVelocity":0.0,"holonomicAngularVelocity":0.0},{"time":1.5566702619680182,"pose":{"rotation":{"radians":0.0},"translation":{"x":4.238836316160004,"y":1.07}},"velocity":2.9319536463457254,"acceleration":-2.0,"curvature":0,"holonomicRotation":180.0,"angularVelocity":0.0,"holonomicAngularVelocity":0.0},{"time":1.5640060290342048,"pose":{"rotation":{"radians":0.0},"translation":{"x":4.260290631680004,"y":1.07}},"velocity":2.917282112213352,"acceleration":-2.0,"curvature":0,"holonomicRotation":180.0,"angularVelocity":0.0,"holonomicAngularVelocity":0.0},{"time":1.5713759495083972,"pose":{"rotation":{"radians":0.0},"translation":{"x":4.281736453120004,"y":1.07}},"velocity":2.9025422712649673,"acceleration":-2.0,"curvature":0,"holonomicRotation":180.0,"angularVelocity":0.0,"holonomicAngularVelocity":0.0},{"time":1.5787801261727084,"pose":{"rotation":{"radians":0.0},"translation":{"x":4.303172567040004,"y":1.07}},"velocity":2.8877339179363455,"acceleration":-1.99999999999994,"curvature":0,"holonomicRotation":180.0,"angularVelocity":0.0,"holonomicAngularVelocity":0.0},{"time":1.586218666374391,"pose":{"rotation":{"radians":0.0},"translation":{"x":4.324597760000004,"y":1.07}},"velocity":2.8728568375329804,"acceleration":-2.0,"curvature":0,"holonomicRotation":180.0,"angularVelocity":0.0,"holonomicAngularVelocity":0.0},{"time":1.593691682169886,"pose":{"rotation":{"radians":0.0},"translation":{"x":4.346010818560004,"y":1.07}},"velocity":2.85791080594199,"acceleration":-2.0,"curvature":0,"holonomicRotation":180.0,"angularVelocity":0.0,"holonomicAngularVelocity":0.0},{"time":1.6011992904751753,"pose":{"rotation":{"radians":0.0},"translation":{"x":4.367410529280004,"y":1.07}},"velocity":2.842895589331412,"acceleration":-1.999999999999941,"curvature":0,"holonomicRotation":180.0,"angularVelocity":0.0,"holonomicAngularVelocity":0.0},{"time":1.608741613222762,"pose":{"rotation":{"radians":0.0},"translation":{"x":4.388795678720004,"y":1.07}},"velocity":2.8278109438362384,"acceleration":-2.0,"curvature":0,"holonomicRotation":180.0,"angularVelocity":0.0,"holonomicAngularVelocity":0.0},{"time":1.616318777525622,"pose":{"rotation":{"radians":0.0},"translation":{"x":4.410165053440004,"y":1.07}},"velocity":2.8126566152305186,"acceleration":-2.0,"curvature":0,"holonomicRotation":180.0,"angularVelocity":0.0,"holonomicAngularVelocity":0.0},{"time":1.6239309158484838,"pose":{"rotation":{"radians":0.0},"translation":{"x":4.431517440000004,"y":1.07}},"velocity":2.7974323385847955,"acceleration":-1.9999999999999416,"curvature":0,"holonomicRotation":180.0,"angularVelocity":0.0,"holonomicAngularVelocity":0.0},{"time":1.631578166186828,"pose":{"rotation":{"radians":0.0},"translation":{"x":4.4528516249600045,"y":1.07}},"velocity":2.7821378379081065,"acceleration":-2.000000000000058,"curvature":0,"holonomicRotation":180.0,"angularVelocity":0.0,"holonomicAngularVelocity":0.0},{"time":1.6392606722540124,"pose":{"rotation":{"radians":0.0},"translation":{"x":4.474166394880005,"y":1.07}},"velocity":2.766772825773738,"acceleration":-2.0,"curvature":0,"holonomicRotation":180.0,"angularVelocity":0.0,"holonomicAngularVelocity":0.0},{"time":1.646978583676957,"pose":{"rotation":{"radians":0.0},"translation":{"x":4.495460536320004,"y":1.07}},"velocity":2.7513370029278486,"acceleration":-2.0,"curvature":0,"holonomicRotation":180.0,"angularVelocity":0.0,"holonomicAngularVelocity":0.0},{"time":1.6547320562008527,"pose":{"rotation":{"radians":0.0},"translation":{"x":4.516732835840004,"y":1.07}},"velocity":2.735830057880057,"acceleration":-2.0,"curvature":0,"holonomicRotation":180.0,"angularVelocity":0.0,"holonomicAngularVelocity":0.0},{"time":1.6625212519033832,"pose":{"rotation":{"radians":0.0},"translation":{"x":4.537982080000004,"y":1.07}},"velocity":2.7202516664749963,"acceleration":-2.0,"curvature":0,"holonomicRotation":180.0,"angularVelocity":0.0,"holonomicAngularVelocity":0.0},{"time":1.6703463394189844,"pose":{"rotation":{"radians":0.0},"translation":{"x":4.559207055360004,"y":1.07}},"velocity":2.704601491443794,"acceleration":-2.0,"curvature":0,"holonomicRotation":180.0,"angularVelocity":0.0,"holonomicAngularVelocity":0.0},{"time":1.6782074941737013,"pose":{"rotation":{"radians":0.0},"translation":{"x":4.5804065484800045,"y":1.07}},"velocity":2.68887918193436,"acceleration":-2.0,"curvature":0,"holonomicRotation":180.0,"angularVelocity":0.0,"holonomicAngularVelocity":0.0},{"time":1.6861048986312306,"pose":{"rotation":{"radians":0.0},"translation":{"x":4.601579345920005,"y":1.07}},"velocity":2.6730843730193015,"acceleration":-2.0,"curvature":0,"holonomicRotation":180.0,"angularVelocity":0.0,"holonomicAngularVelocity":0.0},{"time":1.6940387425507866,"pose":{"rotation":{"radians":0.0},"translation":{"x":4.622724234240004,"y":1.07}},"velocity":2.6572166851801895,"acceleration":-2.0,"curvature":0,"holonomicRotation":180.0,"angularVelocity":0.0,"holonomicAngularVelocity":0.0},{"time":1.7020092232574662,"pose":{"rotation":{"radians":0.0},"translation":{"x":4.643840000000004,"y":1.07}},"velocity":2.6412757237668303,"acceleration":-2.0,"curvature":0,"holonomicRotation":180.0,"angularVelocity":0.0,"holonomicAngularVelocity":0.0},{"time":1.710016545925829,"pose":{"rotation":{"radians":0.0},"translation":{"x":4.664925429760004,"y":1.07}},"velocity":2.6252610784301047,"acceleration":-2.0,"curvature":0,"holonomicRotation":180.0,"angularVelocity":0.0,"holonomicAngularVelocity":0.0},{"time":1.7180609238774718,"pose":{"rotation":{"radians":0.0},"translation":{"x":4.685979310080004,"y":1.07}},"velocity":2.609172322526819,"acceleration":-2.0,"curvature":0,"holonomicRotation":180.0,"angularVelocity":0.0,"holonomicAngularVelocity":0.0},{"time":1.7261425788934104,"pose":{"rotation":{"radians":0.0},"translation":{"x":4.707000427520004,"y":1.07}},"velocity":2.593009012494942,"acceleration":-2.0,"curvature":0,"holonomicRotation":180.0,"angularVelocity":0.0,"holonomicAngularVelocity":0.0},{"time":1.7342617415421588,"pose":{"rotation":{"radians":0.0},"translation":{"x":4.727987568640004,"y":1.07}},"velocity":2.576770687197445,"acceleration":-2.0,"curvature":0,"holonomicRotation":180.0,"angularVelocity":0.0,"holonomicAngularVelocity":0.0},{"time":1.7424186515244433,"pose":{"rotation":{"radians":0.0},"translation":{"x":4.748939520000004,"y":1.07}},"velocity":2.560456867232876,"acceleration":-2.0,"curvature":0,"holonomicRotation":180.0,"angularVelocity":0.0,"holonomicAngularVelocity":0.0},{"time":1.7506135580355622,"pose":{"rotation":{"radians":0.0},"translation":{"x":4.769855068160004,"y":1.07}},"velocity":2.5440670542106383,"acceleration":-2.0,"curvature":0,"holonomicRotation":180.0,"angularVelocity":0.0,"holonomicAngularVelocity":0.0},{"time":1.7588467201464735,"pose":{"rotation":{"radians":0.0},"translation":{"x":4.790732999680004,"y":1.07}},"velocity":2.5276007299888157,"acceleration":-2.0,"curvature":0,"holonomicRotation":180.0,"angularVelocity":0.0,"holonomicAngularVelocity":0.0},{"time":1.7671184072047703,"pose":{"rotation":{"radians":0.0},"translation":{"x":4.811572101120004,"y":1.07}},"velocity":2.511057355872222,"acceleration":-2.0,"curvature":0,"holonomicRotation":180.0,"angularVelocity":0.0,"holonomicAngularVelocity":0.0},{"time":1.7754288992567921,"pose":{"rotation":{"radians":0.0},"translation":{"x":4.8323711590400045,"y":1.07}},"velocity":2.4944363717681783,"acceleration":-2.0,"curvature":0,"holonomicRotation":180.0,"angularVelocity":0.0,"holonomicAngularVelocity":0.0},{"time":1.7837784874922045,"pose":{"rotation":{"radians":0.0},"translation":{"x":4.853128960000004,"y":1.07}},"velocity":2.4777371952973537,"acceleration":-2.0,"curvature":0,"holonomicRotation":180.0,"angularVelocity":0.0,"holonomicAngularVelocity":0.0},{"time":1.7921674747124925,"pose":{"rotation":{"radians":0.0},"translation":{"x":4.873844290560004,"y":1.07}},"velocity":2.4609592208567777,"acceleration":-2.0,"curvature":0,"holonomicRotation":180.0,"angularVelocity":0.0,"holonomicAngularVelocity":0.0},{"time":1.8005961758249072,"pose":{"rotation":{"radians":0.0},"translation":{"x":4.894515937280004,"y":1.07}},"velocity":2.4441018186319483,"acceleration":-2.0,"curvature":0,"holonomicRotation":180.0,"angularVelocity":0.0,"holonomicAngularVelocity":0.0},{"time":1.8090649183635348,"pose":{"rotation":{"radians":0.0},"translation":{"x":4.915142686720004,"y":1.07}},"velocity":2.427164333554693,"acceleration":-2.0,"curvature":0,"holonomicRotation":180.0,"angularVelocity":0.0,"holonomicAngularVelocity":0.0},{"time":1.8175740430392837,"pose":{"rotation":{"radians":0.0},"translation":{"x":4.935723325440004,"y":1.07}},"velocity":2.4101460842031956,"acceleration":-1.9999999999999478,"curvature":0,"holonomicRotation":180.0,"angularVelocity":0.0,"holonomicAngularVelocity":0.0},{"time":1.826123904320719,"pose":{"rotation":{"radians":0.0},"translation":{"x":4.956256640000004,"y":1.07}},"velocity":2.3930463616403252,"acceleration":-2.0,"curvature":0,"holonomicRotation":180.0,"angularVelocity":0.0,"holonomicAngularVelocity":0.0},{"time":1.834714871047839,"pose":{"rotation":{"radians":0.0},"translation":{"x":4.976741416960005,"y":1.07}},"velocity":2.3758644281860857,"acceleration":-1.9999999999999483,"curvature":0,"holonomicRotation":180.0,"angularVelocity":0.0,"holonomicAngularVelocity":0.0},{"time":1.8433473270810403,"pose":{"rotation":{"radians":0.0},"translation":{"x":4.997176442880003,"y":1.07}},"velocity":2.358599516119683,"acceleration":-2.0,"curvature":0,"holonomicRotation":180.0,"angularVelocity":0.0,"holonomicAngularVelocity":0.0},{"time":1.8520216719877245,"pose":{"rotation":{"radians":0.0},"translation":{"x":5.017560504320004,"y":1.07}},"velocity":2.341250826306314,"acceleration":-2.000000000000051,"curvature":0,"holonomicRotation":180.0,"angularVelocity":0.0,"holonomicAngularVelocity":0.0},{"time":1.8607383217691615,"pose":{"rotation":{"radians":0.0},"translation":{"x":5.037892387840004,"y":1.07}},"velocity":2.32381752674344,"acceleration":-2.0,"curvature":0,"holonomicRotation":180.0,"angularVelocity":0.0,"holonomicAngularVelocity":0.0},{"time":1.8694977096304928,"pose":{"rotation":{"radians":0.0},"translation":{"x":5.058170880000004,"y":1.07}},"velocity":2.3062987510207775,"acceleration":-2.0,"curvature":0,"holonomicRotation":180.0,"angularVelocity":0.0,"holonomicAngularVelocity":0.0},{"time":1.8783002867969532,"pose":{"rotation":{"radians":0.0},"translation":{"x":5.078394767360004,"y":1.07}},"velocity":2.2886935966878568,"acceleration":-2.0,"curvature":0,"holonomicRotation":180.0,"angularVelocity":0.0,"holonomicAngularVelocity":0.0},{"time":1.8871465233796823,"pose":{"rotation":{"radians":0.0},"translation":{"x":5.098562836480005,"y":1.07}},"velocity":2.2710011235223986,"acceleration":-2.0,"curvature":0,"holonomicRotation":180.0,"angularVelocity":0.0,"holonomicAngularVelocity":0.0},{"time":1.8960369092947726,"pose":{"rotation":{"radians":0.0},"translation":{"x":5.118673873920003,"y":1.07}},"velocity":2.253220351692218,"acceleration":-2.0,"curvature":0,"holonomicRotation":180.0,"angularVelocity":0.0,"holonomicAngularVelocity":0.0},{"time":1.9049719552395314,"pose":{"rotation":{"radians":0.0},"translation":{"x":5.138726666240004,"y":1.07}},"velocity":2.2353502598027,"acceleration":-2.0,"curvature":0,"holonomicRotation":180.0,"angularVelocity":0.0,"holonomicAngularVelocity":0.0},{"time":1.9139521937302644,"pose":{"rotation":{"radians":0.0},"translation":{"x":5.158720000000003,"y":1.07}},"velocity":2.2173897828212343,"acceleration":-2.0,"curvature":0,"holonomicRotation":180.0,"angularVelocity":0.0,"holonomicAngularVelocity":0.0},{"time":1.92297818020631,"pose":{"rotation":{"radians":0.0},"translation":{"x":5.178652661760004,"y":1.07}},"velocity":2.199337809869143,"acceleration":-2.0,"curvature":0,"holonomicRotation":180.0,"angularVelocity":0.0,"holonomicAngularVelocity":0.0},{"time":1.9320504942054433,"pose":{"rotation":{"radians":0.0},"translation":{"x":5.198523438080004,"y":1.07}},"velocity":2.1811931818708765,"acceleration":-2.0,"curvature":0,"holonomicRotation":180.0,"angularVelocity":0.0,"holonomicAngularVelocity":0.0},{"time":1.9411697406162722,"pose":{"rotation":{"radians":0.0},"translation":{"x":5.218331115520003,"y":1.07}},"velocity":2.162954689049218,"acceleration":-2.000000000000049,"curvature":0,"holonomicRotation":180.0,"angularVelocity":0.0,"holonomicAngularVelocity":0.0},{"time":1.9503365510137565,"pose":{"rotation":{"radians":0.0},"translation":{"x":5.2380744806400035,"y":1.07}},"velocity":2.1446210682542497,"acceleration":-2.0,"curvature":0,"holonomicRotation":180.0,"angularVelocity":0.0,"holonomicAngularVelocity":0.0},{"time":1.9595515850845604,"pose":{"rotation":{"radians":0.0},"translation":{"x":5.257752320000004,"y":1.07}},"velocity":2.126191000112642,"acceleration":-2.0,"curvature":0,"holonomicRotation":180.0,"angularVelocity":0.0,"holonomicAngularVelocity":0.0},{"time":1.9688155321496077,"pose":{"rotation":{"radians":0.0},"translation":{"x":5.277363420160004,"y":1.07}},"velocity":2.1076631059825472,"acceleration":-2.0,"curvature":0,"holonomicRotation":180.0,"angularVelocity":0.0,"holonomicAngularVelocity":0.0},{"time":1.9781291127919134,"pose":{"rotation":{"radians":0.0},"translation":{"x":5.296906567680004,"y":1.07}},"velocity":2.089035944697936,"acceleration":-2.0,"curvature":0,"holonomicRotation":180.0,"angularVelocity":0.0,"holonomicAngularVelocity":0.0},{"time":1.987493080598562,"pose":{"rotation":{"radians":0.0},"translation":{"x":5.316380549120003,"y":1.07}},"velocity":2.0703080090846386,"acceleration":-2.0,"curvature":0,"holonomicRotation":180.0,"angularVelocity":0.0,"holonomicAngularVelocity":0.0},{"time":1.9969082240266114,"pose":{"rotation":{"radians":0.0},"translation":{"x":5.335784151040004,"y":1.07}},"velocity":2.05147772222854,"acceleration":-2.0,"curvature":0,"holonomicRotation":180.0,"angularVelocity":0.0,"holonomicAngularVelocity":0.0},{"time":2.006375368403669,"pose":{"rotation":{"radians":0.0},"translation":{"x":5.355116160000003,"y":1.07}},"velocity":2.032543433474424,"acceleration":-2.000000000000047,"curvature":0,"holonomicRotation":180.0,"angularVelocity":0.0,"holonomicAngularVelocity":0.0},{"time":2.015895378075033,"pose":{"rotation":{"radians":0.0},"translation":{"x":5.374375362560004,"y":1.07}},"velocity":2.013503414131696,"acceleration":-2.0,"curvature":0,"holonomicRotation":180.0,"angularVelocity":0.0,"holonomicAngularVelocity":0.0},{"time":2.025469158710498,"pose":{"rotation":{"radians":0.0},"translation":{"x":5.393560545280004,"y":1.07}},"velocity":1.9943558528607663,"acceleration":-2.000000000000023,"curvature":0,"holonomicRotation":180.0,"angularVelocity":0.0,"holonomicAngularVelocity":0.0},{"time":2.0350976597853707,"pose":{"rotation":{"radians":0.0},"translation":{"x":5.412670494720004,"y":1.07}},"velocity":1.975098850711021,"acceleration":-1.9999999999999538,"curvature":0,"holonomicRotation":180.0,"angularVelocity":0.0,"holonomicAngularVelocity":0.0},{"time":2.044781877251778,"pose":{"rotation":{"radians":0.0},"translation":{"x":5.431703997440003,"y":1.07}},"velocity":1.9557304157782072,"acceleration":-1.999999999999954,"curvature":0,"holonomicRotation":180.0,"angularVelocity":0.0,"holonomicAngularVelocity":0.0},{"time":2.0545228564181417,"pose":{"rotation":{"radians":0.0},"translation":{"x":5.450659840000004,"y":1.07}},"velocity":1.936248457445479,"acceleration":-2.0000000000000457,"curvature":0,"holonomicRotation":180.0,"angularVelocity":0.0,"holonomicAngularVelocity":0.0},{"time":2.064321695056699,"pose":{"rotation":{"radians":0.0},"translation":{"x":5.469536808960003,"y":1.07}},"velocity":1.9166507801683648,"acceleration":-1.9999999999999774,"curvature":0,"holonomicRotation":180.0,"angularVelocity":0.0,"holonomicAngularVelocity":0.0},{"time":2.074179546761207,"pose":{"rotation":{"radians":0.0},"translation":{"x":5.488333690880004,"y":1.07}},"velocity":1.896935076759349,"acceleration":-1.9999999999999776,"curvature":0,"holonomicRotation":180.0,"angularVelocity":0.0,"holonomicAngularVelocity":0.0},{"time":2.084097624579532,"pose":{"rotation":{"radians":0.0},"translation":{"x":5.507049272320003,"y":1.07}},"velocity":1.8770989211226985,"acceleration":-2.000000000000045,"curvature":0,"holonomicRotation":180.0,"angularVelocity":0.0,"holonomicAngularVelocity":0.0},{"time":2.0940772049487655,"pose":{"rotation":{"radians":0.0},"translation":{"x":5.525682339840003,"y":1.07}},"velocity":1.8571397603842312,"acceleration":-2.000000000000022,"curvature":0,"holonomicRotation":180.0,"angularVelocity":0.0,"holonomicAngularVelocity":0.0},{"time":2.104119631963787,"pose":{"rotation":{"radians":0.0},"translation":{"x":5.544231680000004,"y":1.07}},"velocity":1.8370549063541888,"acceleration":-1.9999999999999558,"curvature":0,"holonomicRotation":180.0,"angularVelocity":0.0,"holonomicAngularVelocity":0.0},{"time":2.1142263220140145,"pose":{"rotation":{"radians":0.0},"translation":{"x":5.562696079360004,"y":1.07}},"velocity":1.8168415262537339,"acceleration":-1.999999999999978,"curvature":0,"holonomicRotation":180.0,"angularVelocity":0.0,"holonomicAngularVelocity":0.0},{"time":2.1243987688274024,"pose":{"rotation":{"radians":0.0},"translation":{"x":5.581074324480003,"y":1.07}},"velocity":1.7964966326269582,"acceleration":-1.9999999999999782,"curvature":0,"holonomicRotation":180.0,"angularVelocity":0.0,"holonomicAngularVelocity":0.0},{"time":2.1346385489656936,"pose":{"rotation":{"radians":0.0},"translation":{"x":5.599365201920003,"y":1.07}},"velocity":1.7760170723503756,"acceleration":-2.0000000000000218,"curvature":0,"holonomicRotation":180.0,"angularVelocity":0.0,"holonomicAngularVelocity":0.0},{"time":2.1449473278206463,"pose":{"rotation":{"radians":0.0},"translation":{"x":5.617567498240003,"y":1.07}},"velocity":1.7553995146404704,"acceleration":-1.9999999999999785,"curvature":0,"holonomicRotation":180.0,"angularVelocity":0.0,"holonomicAngularVelocity":0.0},{"time":2.1553268661675204,"pose":{"rotation":{"radians":0.0},"translation":{"x":5.635680000000004,"y":1.07}},"velocity":1.734640437946722,"acceleration":-2.0000000000000213,"curvature":0,"holonomicRotation":180.0,"angularVelocity":0.0,"holonomicAngularVelocity":0.0},{"time":2.165779027339682,"pose":{"rotation":{"radians":0.0},"translation":{"x":5.653701493760003,"y":1.07}},"velocity":1.713736115602399,"acceleration":-1.9999999999999576,"curvature":0,"holonomicRotation":180.0,"angularVelocity":0.0,"holonomicAngularVelocity":0.0},{"time":2.176305785096981,"pose":{"rotation":{"radians":0.0},"translation":{"x":5.671630766080003,"y":1.07}},"velocity":1.6926826000878012,"acceleration":-2.000000000000021,"curvature":0,"holonomicRotation":180.0,"angularVelocity":0.0,"holonomicAngularVelocity":0.0},{"time":2.1869092322707364,"pose":{"rotation":{"radians":0.0},"translation":{"x":5.689466603520003,"y":1.07}},"velocity":1.6714757057402898,"acceleration":-2.0000000000000417,"curvature":0,"holonomicRotation":180.0,"angularVelocity":0.0,"holonomicAngularVelocity":0.0},{"time":2.1975915902800813,"pose":{"rotation":{"radians":0.0},"translation":{"x":5.707207792640004,"y":1.07}},"velocity":1.6501109897215998,"acceleration":-2.000000000000021,"curvature":0,"holonomicRotation":180.0,"angularVelocity":0.0,"holonomicAngularVelocity":0.0},{"time":2.2083552196282747,"pose":{"rotation":{"radians":0.0},"translation":{"x":5.724853120000002,"y":1.07}},"velocity":1.628583731025213,"acceleration":-2.0,"curvature":0,"holonomicRotation":180.0,"angularVelocity":0.0,"holonomicAngularVelocity":0.0},{"time":2.2192026315039173,"pose":{"rotation":{"radians":0.0},"translation":{"x":5.742401372160003,"y":1.07}},"velocity":1.6068889072739283,"acceleration":-1.9999999999999591,"curvature":0,"holonomicRotation":180.0,"angularVelocity":0.0,"holonomicAngularVelocity":0.0},{"time":2.2301365006311222,"pose":{"rotation":{"radians":0.0},"translation":{"x":5.759851335680003,"y":1.07}},"velocity":1.5850211690195182,"acceleration":-2.0000000000000204,"curvature":0,"holonomicRotation":180.0,"angularVelocity":0.0,"holonomicAngularVelocity":0.0},{"time":2.241159679535391,"pose":{"rotation":{"radians":0.0},"translation":{"x":5.777201797120004,"y":1.07}},"velocity":1.56297481121098,"acceleration":-2.00000000000002,"curvature":0,"holonomicRotation":180.0,"angularVelocity":0.0,"holonomicAngularVelocity":0.0},{"time":2.2522752144186953,"pose":{"rotation":{"radians":0.0},"translation":{"x":5.794451543040003,"y":1.07}},"velocity":1.540743741444372,"acceleration":-1.99999999999998,"curvature":0,"holonomicRotation":180.0,"angularVelocity":0.0,"holonomicAngularVelocity":0.0},{"time":2.2634863628692403,"pose":{"rotation":{"radians":0.0},"translation":{"x":5.811599360000003,"y":1.07}},"velocity":1.5183214445432824,"acceleration":-1.9999999999999605,"curvature":0,"holonomicRotation":180.0,"angularVelocity":0.0,"holonomicAngularVelocity":0.0},{"time":2.2747966136694786,"pose":{"rotation":{"radians":0.0},"translation":{"x":5.8286440345600035,"y":1.07}},"velocity":1.495700942942806,"acceleration":-1.9999999999999805,"curvature":0,"holonomicRotation":180.0,"angularVelocity":0.0,"holonomicAngularVelocity":0.0},{"time":2.286209709011723,"pose":{"rotation":{"radians":0.0},"translation":{"x":5.845584353280003,"y":1.07}},"velocity":1.4728747522583177,"acceleration":-1.9999999999999611,"curvature":0,"holonomicRotation":180.0,"angularVelocity":0.0,"holonomicAngularVelocity":0.0},{"time":2.2977296694858294,"pose":{"rotation":{"radians":0.0},"translation":{"x":5.862419102720003,"y":1.07}},"velocity":1.449834831310105,"acceleration":-2.0,"curvature":0,"holonomicRotation":180.0,"angularVelocity":0.0,"holonomicAngularVelocity":0.0},{"time":2.3093608222702167,"pose":{"rotation":{"radians":0.0},"translation":{"x":5.879147069440004,"y":1.07}},"velocity":1.4265725257413304,"acceleration":-2.0,"curvature":0,"holonomicRotation":180.0,"angularVelocity":0.0,"holonomicAngularVelocity":0.0},{"time":2.321107833038763,"pose":{"rotation":{"radians":0.0},"translation":{"x":5.895767040000003,"y":1.07}},"velocity":1.4030785042042384,"acceleration":-1.9999999999999623,"curvature":0,"holonomicRotation":180.0,"angularVelocity":0.0,"holonomicAngularVelocity":0.0},{"time":2.332975742195563,"pose":{"rotation":{"radians":0.0},"translation":{"x":5.912277800960004,"y":1.07}},"velocity":1.379342685890638,"acceleration":-2.0000000000000187,"curvature":0,"holonomicRotation":180.0,"angularVelocity":0.0,"holonomicAngularVelocity":0.0},{"time":2.3449700061718497,"pose":{"rotation":{"radians":0.0},"translation":{"x":5.928678138880003,"y":1.07}},"velocity":1.355354157938065,"acceleration":-1.999999999999963,"curvature":0,"holonomicRotation":180.0,"angularVelocity":0.0,"holonomicAngularVelocity":0.0},{"time":2.3570965446708136,"pose":{"rotation":{"radians":0.0},"translation":{"x":5.944966840320003,"y":1.07}},"velocity":1.3311010809401376,"acceleration":-1.9999999999999634,"curvature":0,"holonomicRotation":180.0,"angularVelocity":0.0,"holonomicAngularVelocity":0.0},{"time":2.369361794934528,"pose":{"rotation":{"radians":0.0},"translation":{"x":5.961142691840003,"y":1.07}},"velocity":1.3065705804127088,"acceleration":-2.0,"curvature":0,"holonomicRotation":180.0,"angularVelocity":0.0,"holonomicAngularVelocity":0.0},{"time":2.3817727743435158,"pose":{"rotation":{"radians":0.0},"translation":{"x":5.977204480000004,"y":1.07}},"velocity":1.2817486215947334,"acceleration":-2.0,"curvature":0,"holonomicRotation":180.0,"angularVelocity":0.0,"holonomicAngularVelocity":0.0},{"time":2.3943371529577275,"pose":{"rotation":{"radians":0.0},"translation":{"x":5.993150991360003,"y":1.07}},"velocity":1.2566198643663093,"acceleration":-2.0000000000000355,"curvature":0,"holonomicRotation":180.0,"angularVelocity":0.0,"holonomicAngularVelocity":0.0},{"time":2.4070633379870117,"pose":{"rotation":{"radians":0.0},"translation":{"x":6.008981012480003,"y":1.07}},"velocity":1.2311674943077406,"acceleration":-2.000000000000035,"curvature":0,"holonomicRotation":180.0,"angularVelocity":0.0,"holonomicAngularVelocity":0.0},{"time":2.4199605726652824,"pose":{"rotation":{"radians":0.0},"translation":{"x":6.0246933299200025,"y":1.07}},"velocity":1.2053730249511987,"acceleration":-2.0000000000000346,"curvature":0,"holonomicRotation":180.0,"angularVelocity":0.0,"holonomicAngularVelocity":0.0},{"time":2.433039052631148,"pose":{"rotation":{"radians":0.0},"translation":{"x":6.040286730240004,"y":1.07}},"velocity":1.179216065019468,"acceleration":-1.9999999999999831,"curvature":0,"holonomicRotation":180.0,"angularVelocity":0.0,"holonomicAngularVelocity":0.0},{"time":2.446310063737606,"pose":{"rotation":{"radians":0.0},"translation":{"x":6.055760000000003,"y":1.07}},"velocity":1.152674042806552,"acceleration":-2.0,"curvature":0,"holonomicRotation":180.0,"angularVelocity":0.0,"holonomicAngularVelocity":0.0},{"time":2.4597861462936392,"pose":{"rotation":{"radians":0.0},"translation":{"x":6.071111925760004,"y":1.07}},"velocity":1.125721877694485,"acceleration":-2.0000000000000164,"curvature":0,"holonomicRotation":180.0,"angularVelocity":0.0,"holonomicAngularVelocity":0.0},{"time":2.4734812921785014,"pose":{"rotation":{"radians":0.0},"translation":{"x":6.086341294080003,"y":1.07}},"velocity":1.098331585924761,"acceleration":-1.9999999999999676,"curvature":0,"holonomicRotation":180.0,"angularVelocity":0.0,"holonomicAngularVelocity":0.0},{"time":2.487411183206043,"pose":{"rotation":{"radians":0.0},"translation":{"x":6.101446891520003,"y":1.07}},"velocity":1.0704718038696777,"acceleration":-2.000000000000016,"curvature":0,"holonomicRotation":180.0,"angularVelocity":0.0,"holonomicAngularVelocity":0.0},{"time":2.501593481756354,"pose":{"rotation":{"radians":0.0},"translation":{"x":6.1164275046400025,"y":1.07}},"velocity":1.0421072067690555,"acceleration":-2.0,"curvature":0,"holonomicRotation":180.0,"angularVelocity":0.0,"holonomicAngularVelocity":0.0},{"time":2.5160481883398726,"pose":{"rotation":{"radians":0.0},"translation":{"x":6.131281920000004,"y":1.07}},"velocity":1.0131977936020184,"acceleration":-2.0,"curvature":0,"holonomicRotation":180.0,"angularVelocity":0.0,"holonomicAngularVelocity":0.0},{"time":2.5307980858738293,"pose":{"rotation":{"radians":0.0},"translation":{"x":6.146008924160002,"y":1.07}},"velocity":0.9836979985341054,"acceleration":-1.999999999999985,"curvature":0,"holonomicRotation":180.0,"angularVelocity":0.0,"holonomicAngularVelocity":0.0},{"time":2.5458692977388253,"pose":{"rotation":{"radians":0.0},"translation":{"x":6.160607303680003,"y":1.07}},"velocity":0.953555574804113,"acceleration":-2.000000000000022,"curvature":0,"holonomicRotation":180.0,"angularVelocity":0.0,"holonomicAngularVelocity":0.0},{"time":2.5612919972530377,"pose":{"rotation":{"radians":0.0},"translation":{"x":6.175075845120003,"y":1.07}},"velocity":0.922710175775688,"acceleration":-2.000000000000014,"curvature":0,"holonomicRotation":180.0,"angularVelocity":0.0,"holonomicAngularVelocity":0.0},{"time":2.5771013218347987,"pose":{"rotation":{"radians":0.0},"translation":{"x":6.189413335040003,"y":1.07}},"velocity":0.8910915266121665,"acceleration":-1.9999999999999718,"curvature":0,"holonomicRotation":180.0,"angularVelocity":0.0,"holonomicAngularVelocity":0.0},{"time":2.5933385687566846,"pose":{"rotation":{"radians":0.0},"translation":{"x":6.2036185600000024,"y":1.07}},"velocity":0.8586170327683951,"acceleration":-1.9999999999999796,"curvature":0,"holonomicRotation":180.0,"angularVelocity":0.0,"holonomicAngularVelocity":0.0},{"time":2.6100527860043092,"pose":{"rotation":{"radians":0.0},"translation":{"x":6.217690306560003,"y":1.07}},"velocity":0.8251885982731462,"acceleration":-1.9999999999999734,"curvature":0,"holonomicRotation":180.0,"angularVelocity":0.0,"holonomicAngularVelocity":0.0},{"time":2.6273029300557207,"pose":{"rotation":{"radians":0.0},"translation":{"x":6.231627361280003,"y":1.07}},"velocity":0.7906883101703235,"acceleration":-1.9999999999999871,"curvature":0,"holonomicRotation":180.0,"angularVelocity":0.0,"holonomicAngularVelocity":0.0},{"time":2.64516085821333,"pose":{"rotation":{"radians":0.0},"translation":{"x":6.245428510720004,"y":1.07}},"velocity":0.7549724538551049,"acceleration":-2.000000000000006,"curvature":0,"holonomicRotation":180.0,"angularVelocity":0.0,"holonomicAngularVelocity":0.0},{"time":2.663715586383807,"pose":{"rotation":{"radians":0.0},"translation":{"x":6.259092541440003,"y":1.07}},"velocity":0.7178629975141505,"acceleration":-2.0,"curvature":0,"holonomicRotation":180.0,"angularVelocity":0.0,"holonomicAngularVelocity":0.0},{"time":2.6830795333341766,"pose":{"rotation":{"radians":0.0},"translation":{"x":6.2726182400000035,"y":1.07}},"velocity":0.6791351036134116,"acceleration":-2.0,"curvature":0,"holonomicRotation":180.0,"angularVelocity":0.0,"holonomicAngularVelocity":0.0},{"time":2.703398014226023,"pose":{"rotation":{"radians":0.0},"translation":{"x":6.2860043929600025,"y":1.07}},"velocity":0.6384981418297184,"acceleration":-2.0000000000000164,"curvature":0,"holonomicRotation":180.0,"angularVelocity":0.0,"holonomicAngularVelocity":0.0},{"time":2.7248643197564486,"pose":{"rotation":{"radians":0.0},"translation":{"x":6.299249786880003,"y":1.07}},"velocity":0.5955655307688674,"acceleration":-1.9999999999999896,"curvature":0,"holonomicRotation":180.0,"angularVelocity":0.0,"holonomicAngularVelocity":0.0},{"time":2.7477450045376224,"pose":{"rotation":{"radians":0.0},"translation":{"x":6.312353208320002,"y":1.07}},"velocity":0.54980416120652,"acceleration":-1.9999999999999951,"curvature":0,"holonomicRotation":180.0,"angularVelocity":0.0,"holonomicAngularVelocity":0.0},{"time":2.7724253466767736,"pose":{"rotation":{"radians":0.0},"translation":{"x":6.3253134438400025,"y":1.07}},"velocity":0.5004434769282172,"acceleration":-2.000000000000009,"curvature":0,"holonomicRotation":180.0,"angularVelocity":0.0,"holonomicAngularVelocity":0.0},{"time":2.799498967873447,"pose":{"rotation":{"radians":0.0},"translation":{"x":6.338129280000002,"y":1.07}},"velocity":0.4462962345348706,"acceleration":-1.999999999999998,"curvature":0,"holonomicRotation":180.0,"angularVelocity":0.0,"holonomicAngularVelocity":0.0},{"time":2.829968962667156,"pose":{"rotation":{"radians":0.0},"translation":{"x":6.350799503360003,"y":1.07}},"velocity":0.3853562449474532,"acceleration":-1.9999999999999927,"curvature":0,"holonomicRotation":180.0,"angularVelocity":0.0,"holonomicAngularVelocity":0.0},{"time":2.8657985538758415,"pose":{"rotation":{"radians":0.0},"translation":{"x":6.363322900480003,"y":1.07}},"velocity":0.31369706253008206,"acceleration":-1.9999999999999938,"curvature":0,"holonomicRotation":180.0,"angularVelocity":0.0,"holonomicAngularVelocity":0.0},{"time":2.9120753694085093,"pose":{"rotation":{"radians":0.0},"translation":{"x":6.3756982579200026,"y":1.07}},"velocity":0.22114343146474605,"acceleration":-2.000000000000008,"curvature":0,"holonomicRotation":180.0,"angularVelocity":0.0,"holonomicAngularVelocity":0.0},{"time":3.0226470851408824,"pose":{"rotation":{"radians":0.0},"translation":{"x":6.387924362240003,"y":1.07}},"velocity":0,"acceleration":-1.9999999999999982,"curvature":0,"holonomicRotation":180.0,"angularVelocity":0.0,"holonomicAngularVelocity":0.0}]